Workbook
Name aporte: Planilha1!$D$18
Name dividendos_mensais: Planilha1!$D$22
Name patrimonio: Planilha1!$D$21
Name qtd_anos: Planilha1!$D$19
Name rendimento_carteira: Planilha1!$D$13
Name salario: Planilha1!$D$12
Name sugestao_investimento: Planilha1!$D$14
Name taxa_mensal: Planilha1!$D$20

Sheet Planilha1
B10: CONFIGURAÇÕES
B12: Salário | D12: 2000
B13: Rendimento Carteira | D13: 0.006
B14: Sugestão de Investimento | D14: =salario*30% -> 600
B16: INVESTIMENTO MENSAL
B18: Quanto investir por mes? | D18: 200
B19: Por quantos anos? | D19: 5
B20: Taxa de rendimento mensal? | D20: 0.01079
B21: Patrimônio acumulado? | D21: =FV(taxa_mensal,qtd_anos*12,aporte*-1) -> 16755.383
B22: Divedendos mensais? | D22: =patrimonio*rendimento_carteira -> 100.5323
B24: Cenários | D24: Dividendo
A26: 2 | B26: Quanto em 2 Anos? | C26: =FV($D$20,$A26*12,$D$18*-1) -> 5445.5255 | D26: =C26*rendimento_carteira -> 32.673153
A27: 5 | B27: Quanto em 5 Anos? | C27: =FV($D$20,$A27*12,$D$18*-1) -> 16755.383 | D27: =C27*rendimento_carteira -> 100.5323
A28: 10 | B28: Quanto em 10 Anos? | C28: =FV($D$20,$A28*12,$D$18*-1) -> 48656.843 | D28: =C28*rendimento_carteira -> 291.94106
A29: 20 | B29: Quanto em 20 Anos? | C29: =FV($D$20,$A29*12,$D$18*-1) -> 225039.68 | D29: =C29*rendimento_carteira -> 1350.2381
A30: 30 | B30: Quanto em 30 Anos? | C30: =FV($D$20,$A30*12,$D$18*-1) -> 864433.93 | D30: =C30*rendimento_carteira -> 5186.6036
B32: PERFIL | C32: Agressivo
B33: VALOR A SER INVESTIDO POR MÊS | C33: =aporte -> 200
B35: TIPO DE FII | C35: Percentual Sugerido | D35: Valores
B36: PAPEL | C36: =VLOOKUP($C$32&"-"&B36,Apoio!$A:$D,4,FALSE) -> 0.5 | D36: =C36*C$33 -> 100
B37: TIJOLO | C37: =VLOOKUP($C$32&"-"&B37,Apoio!$A:$D,4,FALSE) -> 0.1 | D37: =C37*C$33 -> 20
B38: HÍBRIDOS | C38: =VLOOKUP($C$32&"-"&B38,Apoio!$A:$D,4,FALSE) -> 0.05 | D38: =C38*C$33 -> 10
B39: FOFs | C39: =VLOOKUP($C$32&"-"&B39,Apoio!$A:$D,4,FALSE) -> 0.05 | D39: =C39*C$33 -> 10
B40: DESENVOLVIMENTO | C40: =VLOOKUP($C$32&"-"&B40,Apoio!$A:$D,4,FALSE) -> 0.2 | D40: =C40*C$33 -> 40
B41: HOTELARIAS | C41: =VLOOKUP($C$32&"-"&B41,Apoio!$A:$D,4,FALSE) -> 0.1 | D41: =C41*C$33 -> 20
D42: =SUM(D36:D41) -> 200

Sheet Apoio
A1: CHAVE | B1: PERFIL | C1: TIPO DE FII | D1: % | H1: %
A2: =B2&"-"&C2 -> Conservador-PAPEL | B2: Conservador | C2: PAPEL | D2: 0.3
A3: =B3&"-"&C3 -> Conservador-TIJOLO | B3: Conservador | C3: TIJOLO | D3: 0.5 | G3: Moderado-TIJOLO | H3: =VLOOKUP(G3,$A:$D,4,FALSE) -> 0.35
A4: =B4&"-"&C4 -> Conservador-HÍBRIDOS | B4: Conservador | C4: HÍBRIDOS | D4: 0.1
A5: =B5&"-"&C5 -> Conservador-FOFs | B5: Conservador | C5: FOFs | D5: 0.1
A6: =B6&"-"&C6 -> Conservador-DESENVOLVIMENTO | B6: Conservador | C6: DESENVOLVIMENTO | D6: 0
A7: =B7&"-"&C7 -> Conservador-HOTELARIAS | B7: Conservador | C7: HOTELARIAS | D7: 0
A8: =B8&"-"&C8 -> Moderado-PAPEL | B8: Moderado | C8: PAPEL | D8: 0.32
A9: =B9&"-"&C9 -> Moderado-TIJOLO | B9: Moderado | C9: TIJOLO | D9: 0.35
A10: =B10&"-"&C10 -> Moderado-HÍBRIDOS | B10: Moderado | C10: HÍBRIDOS | D10: 0.08
A11: =B11&"-"&C11 -> Moderado-FOFs | B11: Moderado | C11: FOFs | D11: 0.05
A12: =B12&"-"&C12 -> Moderado-DESENVOLVIMENTO | B12: Moderado | C12: DESENVOLVIMENTO | D12: 0.1
A13: =B13&"-"&C13 -> Moderado-HOTELARIAS | B13: Moderado | C13: HOTELARIAS | D13: 0.1
A14: =B14&"-"&C14 -> Agressivo-PAPEL | B14: Agressivo | C14: PAPEL | D14: 0.5
A15: =B15&"-"&C15 -> Agressivo-TIJOLO | B15: Agressivo | C15: TIJOLO | D15: 0.1
... A19: =B19&"-"&C19 -> Agressivo-HOTELARIAS | B19: Agressivo | C19: HOTELARIAS | D19: 0.1
